steam_openid/__init__.py
steam_openid/steam_openid.py
steam_openid-1.0.5.dist-info/LICENSE
steam_openid-1.0.5.dist-info/METADATA
steam_openid-1.0.5.dist-info/WHEEL
steam_openid-1.0.5.dist-info/top_level.txt
steam_openid-1.0.5.dist-info/RECORD
