Metadata-Version: 2.1
Name: steam-openid
Version: 1.0.5
Summary: A simple package for integrating Steam OpenID authentication in applications.
Author: imtaas
Project-URL: Homepage, https://github.com/imtaas/steam-openid
Project-URL: Issues, https://github.com/imtaas/steam-openid/issues
Classifier: Programming Language :: Python :: 3
Classifier: License :: OSI Approved :: MIT License
Classifier: Operating System :: OS Independent
Requires-Python: >=3.6
License-File: LICENSE
